{"cmd":"NOTICE_MSG","id":205,"name":"总督不抽奖跑马灯","full":{"head_icon":"https://i0.hdslb.com/bfs/live/eabd148f6cfe4dcf623cba6c44bca0bbfc61d3e1.png","tail_icon":"https://i0.hdslb.com/bfs/live/822da481fdaba986d738db5d8fd469ffa95a8fa1.webp","head_icon_fa":"https://i0.hdslb.com/bfs/live/eabd148f6cfe4dcf623cba6c44bca0bbfc61d3e1.png","tail_icon_fa":"https://i0.hdslb.com/bfs/live/7d7af6107ef808438e6c3b4db0c7868bf78e5172.png","head_icon_fan":1,"tail_icon_fan":4,"background":"#FFB03CFF","color":"#FFFFFFFF","highlight":"#B25AC1FF","time":10},"half":{"head_icon":"","tail_icon":"","background":"","color":"","highlight":"","time":0},"side":{"head_icon":"https://i0.hdslb.com/bfs/live/90c039d6632b224dde9e02b47a3da74dfbdcdb99.png","background":"#FFE9C8FF","color":"#EF903AFF","highlight":"#D54900FF","border":"#FFCFA4FF"},"roomid":25024665,"real_roomid":25024665,"msg_common":"<%我的腿毛很哇塞%>在<%朵朵莓烦恼%>的房间开通了总督","msg_self":"<%我的腿毛很哇塞%> 开通了主播的 <%总督%>","link_url":"https://live.bilibili.com/25024665?accept_quality=%5B10000%2C150%5D&broadcast_type=0&current_qn=150&current_quality=150&is_room_feed=1&live_play_network=other&p2p_type=0&playurl_h264=http%3A%2F%2Fc1--cn-gotcha09.bilivideo.com%2Flive-bvc%2F864978%2Flive_1381336796_36199941_1500.flv%3Fexpires%3D1658637189%26len%3D0%26oi%3D0%26pt%3D%26qn%3D150%26trid%3D1000ba6b308642654763bf08763ec11f9694%26sigparams%3Dcdn%2Cexpires%2Clen%2Coi%2Cpt%2Cqn%2Ctrid%26cdn%3Dcn-gotcha09%26sign%3D3c039c1f04cfc7bcfabd53a04d8b39c5%26sk%3D2935686d6cb9146c7a6a6a0b4e120e250342be3df4dc8310261aab0ce9e21e44%26p2p_type%3D0%26src%3D57345%26sl%3D1%26flowtype%3D1%26source%3Dbatch%26order%3D1%26machinezone%3Dylf%26pp%3Drtmp%26site%3D76314cd91c1cd57ead7876a7c1797e36&playurl_h265=&quality_description=%5B%7B%22qn%22%3A10000%2C%22desc%22%3A%22%E5%8E%9F%E7%94%BB%22%7D%2C%7B%22qn%22%3A150%2C%22desc%22%3A%22%E9%AB%98%E6%B8%85%22%7D%5D&from=28003&extra_jump_from=28003&live_lottery_type=2","msg_type":3,"shield_uid":-1,"business_id":"","scatter":{"min":0,"max":0},"marquee_id":"","notice_type":0}